{
  "preRequisites:11": [
    686
  ],
  "properties:10": {
    "betterquesting:10": {
      "desc:8": "§oWhen engraving it once just isn\u0027t enough§r\n\nThe §aCrystal SoC§r is used to make cheaper §9Crystal Circuits§r. Enjoy the discount!\n\nCrystal SoC\u0027s require §9ZPM Emitters§r, which means you need a §9Data Orb§r for their research.\n\nIn the future, these may become more difficult to make.\n\n§bLore§r: In GT5u, the texture for this item was red, and did not have the special design on it. There was a \"raw\" version with the design, but it was used for other unrelated things. Who knows why!\n\n",
      "icon:10": {
        "Count:3": 1,
        "Damage:2": 705,
        "id:8": "gregtech:meta_item_1"
      },
      "name:8": "Crystal SoC",
      "visibility:8": "ALWAYS"
    }
  },
  "questID:3": 656,
  "tasks:9": {
    "0:10": {
      "index:3": 0,
      "requiredItems:9": {
        "0:10": {
          "Count:3": 1,
          "Damage:2": 705,
          "id:8": "gregtech:meta_item_1"
        }
      },
      "taskID:8": "bq_standard:retrieval"
    }
  }
}